{
  "list":[{
    "ORGID":"08001",
    "ORGNAME_CN":"八里湖支行",
    "ORGLEVELID":"1",
    "PARENTORGID":"00004",
    "ORGTYPEID":"2",
    "BRANCH_STATYS_TYPE":"2"
  },
  {
    "ORGID":"72701",
    "ORGNAME_CN":"八里湖支行",
    "ORGLEVELID":"1",
    "PARENTORGID":"00004",
    "ORGTYPEID":"2",
    "BRANCH_STATYS_TYPE":"2"
  },
  {
    "ORGID":"72702",
    "ORGNAME_CN":"八里湖支行",
    "ORGLEVELID":"1",
    "PARENTORGID":"00004",
    "ORGTYPEID":"2",
    "BRANCH_STATYS_TYPE":"2"
  },
  {
    "ORGID":"72703",
    "ORGNAME_CN":"八里湖支行",
    "ORGLEVELID":"1",
    "PARENTORGID":"00004",
    "ORGTYPEID":"5",
    "BRANCH_STATYS_TYPE":"2"
  },
  {
    "ORGID":"72704",
    "ORGNAME_CN":"八里湖支行",
    "ORGLEVELID":"1",
    "PARENTORGID":"00004",
    "ORGTYPEID":"4",
    "BRANCH_STATYS_TYPE":"2"
  },
  {
    "ORGID":"72705",
    "ORGNAME_CN":"八里湖支行",
    "ORGLEVELID":"1",
    "PARENTORGID":"00004",
    "ORGTYPEID":"3",
    "BRANCH_STATYS_TYPE":"2"
  }]
}